limbus_components/__init__.py
limbus_components/base/__init__.py
limbus_components/base/base.py
limbus_components/kornia/__init__.py
limbus_components/kornia/augmentation/RandomCrop.py
limbus_components/kornia/augmentation/__init__.py
limbus_components/kornia/color/__init__.py
limbus_components/kornia/color/hls_to_rgb.py
limbus_components/kornia/color/rgb_to_hls.py
limbus_components/kornia/contrib/FaceDetector.py
limbus_components/kornia/contrib/__init__.py
limbus_components/kornia/contrib/contrib.py
limbus_components/kornia/contrib/histogram_matching.py
limbus_components/kornia/enhance/__init__.py
limbus_components/kornia/enhance/equalize_clahe.py
limbus_components/kornia/enhance/image_histogram2d.py
limbus_components/kornia/enhance/normalize_min_max.py
limbus_components/kornia/feature/LoFTR.py
limbus_components/kornia/feature/__init__.py
limbus_components/kornia/geometry/__init__.py
limbus_components/kornia/geometry/transform/Affine.py
limbus_components/kornia/geometry/transform/Hflip.py
limbus_components/kornia/geometry/transform/HomographyWarper.py
limbus_components/kornia/geometry/transform/PyrDown.py
limbus_components/kornia/geometry/transform/PyrUp.py
limbus_components/kornia/geometry/transform/Rescale.py
limbus_components/kornia/geometry/transform/Resize.py
limbus_components/kornia/geometry/transform/Rot180.py
limbus_components/kornia/geometry/transform/Rotate.py
limbus_components/kornia/geometry/transform/Scale.py
limbus_components/kornia/geometry/transform/ScalePyramid.py
limbus_components/kornia/geometry/transform/Shear.py
limbus_components/kornia/geometry/transform/Translate.py
limbus_components/kornia/geometry/transform/Vflip.py
limbus_components/kornia/geometry/transform/__init__.py
limbus_components/kornia/geometry/transform/center_crop.py
limbus_components/kornia/geometry/transform/crop_and_resize.py
limbus_components/kornia/geometry/transform/warp_perspective.py
limbus_components/torch/__init__.py
limbus_components/torch/cat.py
limbus_components-0.1.4.dist-info/LICENSE
limbus_components-0.1.4.dist-info/METADATA
limbus_components-0.1.4.dist-info/WHEEL
limbus_components-0.1.4.dist-info/top_level.txt
limbus_components-0.1.4.dist-info/RECORD
