Metadata-Version: 2.1
Name: limbus-components
Version: 0.1.4
Summary: Components to be used with limbus.
Home-page: https://github.com/kornia/limbus-components
Author: Luis Ferraz
License-File: LICENSE
Requires-Dist: limbus (>=0.1.6)
Requires-Dist: torch
Requires-Dist: numpy
Requires-Dist: kornia
Requires-Dist: opencv-python
Requires-Dist: pillow
Provides-Extra: dev
Requires-Dist: pytest ; extra == 'dev'
Requires-Dist: pytest-flake8 ; extra == 'dev'
Requires-Dist: pytest-cov ; extra == 'dev'
Requires-Dist: pytest-mypy ; extra == 'dev'
Requires-Dist: pytest-pydocstyle ; extra == 'dev'
Requires-Dist: pytest-asyncio ; extra == 'dev'
Requires-Dist: mypy ; extra == 'dev'
Requires-Dist: pydocstyle ; extra == 'dev'
Requires-Dist: flake8 (<5.0.0) ; extra == 'dev'
Requires-Dist: pep8-naming ; extra == 'dev'
